.coveragerc
.pre-commit-config.yaml
.travis.yml
AUTHORS
ChangeLog
LICENSE
README.md
requirements-dev.txt
setup.cfg
setup.py
mimics/__init__.py
mimics/constants.py
mimics/deferred.py
mimics/inspect.py
mimics/record.py
mimics.egg-info/PKG-INFO
mimics.egg-info/SOURCES.txt
mimics.egg-info/dependency_links.txt
mimics.egg-info/not-zip-safe
mimics.egg-info/pbr.json
mimics.egg-info/top_level.txt
tests/conftest.py
tests/test_defer_class_definition.py
tests/test_deferred.py
tests/test_use_cases.py