Metadata-Version: 2.1
Name: mimics
Version: 0.0.1
Summary: Small tool for deferring actions and operations on objects and classes
Home-page: https://github.com/maarten-dp/mimics
Author: Maarten De Paepe
Author-email: "maarten.de.paepe@gmail.com"
License: UNKNOWN
Platform: UNKNOWN
Classifier: Development Status :: 4 - Beta
Classifier: Operating System :: MacOS :: MacOS X
Classifier: Operating System :: Microsoft :: Windows
Classifier: Operating System :: POSIX
Classifier: License :: OSI Approved :: MIT License
Classifier: Programming Language :: Python
Classifier: Programming Language :: Python :: 3.6
License-File: LICENSE
